{"id": "median_maintenance", "path": "/Users/dustin/CS/projects/courses/algorithms_courses/course2/assignment3/median_maintenance.py", "mtime": 1569820680, "size": 1383, "hash": "b0c01ec8c9e9d292f3a1312bd58a9793", "data_mtime": 1569790011, "dependencies": ["typing", "heapq", "dataclasses", "builtins", "abc"], "suppressed": [], "child_modules": [], "options": {"implicit_reexport": true, "ignore_errors": false, "disallow_incomplete_defs": false, "show_none_errors": true, "always_true": [], "warn_no_return": true, "ignore_missing_imports": true, "warn_return_any": false, "disallow_any_decorated": false, "strict_optional": true, "strict_equality": false, "disallow_any_generics": false, "follow_imports": "silent", "check_untyped_defs": false, "disallow_any_unimported": false, "bazel": false, "disallow_untyped_defs": false, "disallow_untyped_calls": false, "disallow_untyped_decorators": false, "plugins": [], "follow_imports_for_stubs": false, "new_semantic_analyzer": true, "mypyc": false, "disallow_any_expr": false, "disallow_subclassing_any": false, "warn_unreachable": false, "strict_optional_whitelist": null, "allow_redefinition": false, "platform": "darwin", "disallow_any_explicit": false, "local_partial_types": false, "warn_unused_ignores": false, "no_implicit_optional": false, "allow_untyped_globals": false, "always_false": []}, "dep_prios": [5, 10, 5, 5, 30], "dep_lines": [4, 5, 6, 1, 1], "interface_hash": "6674807ed9a1dabccb3421ea11cf8e7f", "version_id": "0.720", "ignore_all": false}